miniboss/__init__.py
miniboss/context.py
miniboss/docker_client.py
miniboss/exceptions.py
miniboss/main.py
miniboss/py.typed
miniboss/running_context.py
miniboss/service_agent.py
miniboss/services.py
miniboss/types.py
miniboss-0.4.5.dist-info/LICENSE.txt
miniboss-0.4.5.dist-info/METADATA
miniboss-0.4.5.dist-info/WHEEL
miniboss-0.4.5.dist-info/top_level.txt
miniboss-0.4.5.dist-info/RECORD
