Metadata-Version: 2.1
Name: miniboss
Version: 0.4.5
Summary: Containerized app testing framework
Home-page: https://github.com/afroisalreadyinu/miniboss
Author: Ulas Turkmen
License: MIT
Platform: UNKNOWN
Classifier: License :: OSI Approved :: MIT License
Classifier: Development Status :: 3 - Alpha
Classifier: Topic :: Software Development :: Build Tools
Classifier: Topic :: Software Development :: Testing
Classifier: Programming Language :: Python :: 3
Classifier: Intended Audience :: Developers
Requires-Python: >3.8.0
License-File: LICENSE.txt
Requires-Dist: click (>7)
Requires-Dist: docker (>4)
Requires-Dist: furl (>2)
Requires-Dist: requests (>2)
Requires-Dist: attrs (>20)
Requires-Dist: python-slugify (>6.0.0)
